dukron/__init__.py
dukron/_kron.py
dukron/_ops.py
dukron/_partitioner.py
dukron-0.0.0.dist-info/LICENCE
dukron-0.0.0.dist-info/METADATA
dukron-0.0.0.dist-info/WHEEL
dukron-0.0.0.dist-info/RECORD
