Metadata-Version: 2.3
Name: dukron
Version: 0.0.0
Summary: a faster implementation of PSGD Kron second-order optimizer
License: CC-BY-4.0
Author: Erfan Zare Chavoshi
Author-email: Erfanzare810@gmail.com
Requires-Python: >=3.10,<4.0
Classifier: License :: Other/Proprietary License
Classifier: Programming Language :: Python :: 3
Classifier: Programming Language :: Python :: 3.10
Classifier: Programming Language :: Python :: 3.11
Classifier: Programming Language :: Python :: 3.12
Classifier: Programming Language :: Python :: 3.13
Requires-Dist: eformer (>=0.0.13)
Project-URL: Homepage, https://github.com/erfanzar/dukron
